covid19_utpl/.DS_Store
covid19_utpl/__init__.py
covid19_utpl/data/vacunometro_cantones.csv
covid19_utpl/img/Vacunados_Canton.png
covid19_utpl/img/Vacunados_Provincia.png
covid19_utpl/img/Vacunados_Region.png
covid19_utpl/main.py
covid19_utpl/src/__init__.py
covid19_utpl/src/conexion.py
covid19_utpl/src/grafica.py
covid19_utpl/src/listados.py
covid19_utpl/src/vacunados.py
covid19_utpl-1.0.2.dist-info/WHEEL
covid19_utpl-1.0.2.dist-info/METADATA
covid19_utpl-1.0.2.dist-info/RECORD
