Metadata-Version: 2.1
Name: covid19-utpl
Version: 1.0.2
Summary: 
Author: David Jimenez
Requires-Python: >=3.10,<4.0
Classifier: Programming Language :: Python :: 3
Classifier: Programming Language :: Python :: 3.10
